LICENSE.txt
MANIFEST.in
README.md
setup.cfg
setup.py
kinto_github_token/__init__.py
kinto_github_token/authentication.py
kinto_github_token/views.py
kinto_github_token.egg-info/PKG-INFO
kinto_github_token.egg-info/SOURCES.txt
kinto_github_token.egg-info/dependency_links.txt
kinto_github_token.egg-info/top_level.txt