Metadata-Version: 1.1
Name: kinto-github-token
Version: 0.1.1
Summary: Github Authentication support for Kinto
Home-page: https://github.com/ptgamr/kinto-github-token
Author: Anh Trinh
Author-email: anh.trinhtrung@gmail.com
License: UNKNOWN
Platform: UNKNOWN
Classifier: Development Status :: 2 - Pre-Alpha
Classifier: Programming Language :: Python
Classifier: Programming Language :: Python :: 2
Classifier: Programming Language :: Python :: 2.7
Classifier: Programming Language :: Python :: 3
Classifier: Programming Language :: Python :: 3.4
Classifier: Programming Language :: Python :: 3.5
